diffop/__init__.py
diffop/coefs.py
diffop/diff.py
diffop/grids.py
diffop/operators.py
diffop/stencils.py
diffop/utils.py
diffop/vector.py
test/__init__.py
test/test_bugs.py
test/test_coefs.py
test/test_diff.py
test/test_findiff.py
test/test_grids.py
test/test_pde.py
test/test_scaling.py
test/test_utils.py
test/test_vector.py
diffop-4.3.1.dist-info/LICENSE
diffop-4.3.1.dist-info/METADATA
diffop-4.3.1.dist-info/WHEEL
diffop-4.3.1.dist-info/top_level.txt
diffop-4.3.1.dist-info/RECORD
