Metadata-Version: 2.1
Name: diffop
Version: 4.3.1
Summary: A Python package for finite difference derivatives in any number of dimensions.
Home-page: https://github.com/AdwardAllan
Author: Li XinJUN
Author-email: lxjproductivity@gmail.com
License: GNU License
Keywords: finite-differences,numerical-derivatives,scientific-computing
Platform: ALL
Classifier: Intended Audience :: Developers
Classifier: Topic :: Scientific/Engineering :: Mathematics
Classifier: Programming Language :: Python :: 3
Classifier: Programming Language :: Python :: 3.4
Classifier: Programming Language :: Python :: 3.5
Classifier: Programming Language :: Python :: 3.6
Classifier: Programming Language :: Python :: 3.7
Classifier: Programming Language :: Python :: 3.8
Classifier: Programming Language :: Python :: 3.9
Requires-Python: >=3.6
License-File: LICENSE
